src/__init__.py
src/batch_job.py
src/batch_manager.py
src/citations.py
src/core.py
src/types.py
src/utils.py
src/providers/__init__.py
src/providers/anthropic.py
src/providers/base.py
ai_batch-0.2.1.dist-info/METADATA
ai_batch-0.2.1.dist-info/WHEEL
ai_batch-0.2.1.dist-info/entry_points.txt
ai_batch-0.2.1.dist-info/RECORD
