Metadata-Version: 2.4
Name: ai-batch
Version: 0.2.1
Summary: ai-batch is now batchata
Author: Agam More
License: MIT
Classifier: Development Status :: 3 - Alpha
Classifier: Intended Audience :: Developers
Classifier: License :: OSI Approved :: MIT License
Classifier: Programming Language :: Python :: 3
Classifier: Programming Language :: Python :: 3.12
Requires-Python: >=3.12
Requires-Dist: batchata
